envoy/base/command/__init__.py
envoy/base/command/command.py
envoy/base/command/decorators.py
envoy/base/command/py.typed
envoy/base/command/runner.py
tests/test_runner.py
envoy.base.command-0.0.1.dist-info/METADATA
envoy.base.command-0.0.1.dist-info/WHEEL
envoy.base.command-0.0.1.dist-info/top_level.txt
envoy.base.command-0.0.1.dist-info/RECORD
